mcp_agentcore_proxy/__init__.py
mcp_agentcore_proxy/aws_session.py
mcp_agentcore_proxy/client.py
mcp_agentcore_proxy/server.py
mcp_agentcore_proxy/session_manager.py
mcp_agentcore_proxy/version.py
mcp_agentcore_proxy-0.1.5.dist-info/METADATA
mcp_agentcore_proxy-0.1.5.dist-info/WHEEL
mcp_agentcore_proxy-0.1.5.dist-info/entry_points.txt
mcp_agentcore_proxy-0.1.5.dist-info/licenses/LICENSE
mcp_agentcore_proxy-0.1.5.dist-info/RECORD
