Metadata-Version: 2.4
Name: mcp-agentcore-proxy
Version: 0.1.5
Summary: MCP STDIO proxy for Amazon Bedrock AgentCore Runtime
Project-URL: Repository, https://github.com/alessandrobologna/agentcore-mcp-proxy
Author-email: Alessandro Bologna <alessandro.bologna@gmail.com>
Maintainer-email: Alessandro Bologna <alessandro.bologna@gmail.com>
License: MIT License
License-File: LICENSE
Classifier: Development Status :: 4 - Beta
Classifier: Intended Audience :: Developers
Classifier: License :: OSI Approved :: MIT License
Classifier: Programming Language :: Python :: 3
Classifier: Programming Language :: Python :: 3.11
Classifier: Programming Language :: Python :: 3.12
Classifier: Programming Language :: Python :: 3.13
Classifier: Topic :: Software Development :: Libraries :: Python Modules
Requires-Python: >=3.11
Requires-Dist: aws-assume-role-lib>=2.0.0
Requires-Dist: boto3>=1.40.45
Provides-Extra: dev
Requires-Dist: httpx>=0.27.0; extra == 'dev'
Requires-Dist: pytest-asyncio>=0.23.0; extra == 'dev'
Requires-Dist: pytest-mock>=3.12.0; extra == 'dev'
Requires-Dist: pytest>=8.0.0; extra == 'dev'
Provides-Extra: server
Requires-Dist: fastapi>=0.111.0; extra == 'server'
Requires-Dist: uvicorn>=0.37.0; extra == 'server'
